odoo/addons/purchase_price_recalculation/README.rst
odoo/addons/purchase_price_recalculation/__init__.py
odoo/addons/purchase_price_recalculation/__manifest__.py
odoo/addons/purchase_price_recalculation/i18n/purchase_price_recalculation.pot
odoo/addons/purchase_price_recalculation/model/__init__.py
odoo/addons/purchase_price_recalculation/model/purchase_order.py
odoo/addons/purchase_price_recalculation/readme/CONTRIBUTORS.rst
odoo/addons/purchase_price_recalculation/readme/CREDITS.rst
odoo/addons/purchase_price_recalculation/readme/DESCRIPTION.rst
odoo/addons/purchase_price_recalculation/readme/USAGE.rst
odoo/addons/purchase_price_recalculation/static/description/fig1.png
odoo/addons/purchase_price_recalculation/static/description/fig2.png
odoo/addons/purchase_price_recalculation/static/description/icon.png
odoo/addons/purchase_price_recalculation/static/description/index.html
odoo/addons/purchase_price_recalculation/view/actions_server.xml
odoo12_addon_purchase_price_recalculation-12.0.1.0.0.99.dev3.dist-info/METADATA
odoo12_addon_purchase_price_recalculation-12.0.1.0.0.99.dev3.dist-info/WHEEL
odoo12_addon_purchase_price_recalculation-12.0.1.0.0.99.dev3.dist-info/top_level.txt
odoo12_addon_purchase_price_recalculation-12.0.1.0.0.99.dev3.dist-info/RECORD
